message_sender/__init__.py
message_sender/admin.py
message_sender/apps.py
message_sender/factory.py
message_sender/formatters.py
message_sender/models.py
message_sender/serializers.py
message_sender/signals.py
message_sender/tasks.py
message_sender/test_tasks.py
message_sender/test_utils.py
message_sender/tests.py
message_sender/urls.py
message_sender/utils.py
message_sender/views.py
message_sender/management/__init__.py
message_sender/management/commands/__init__.py
message_sender/management/commands/importcsv.py
message_sender/management/commands/update_identity_field.py
message_sender/migrations/0001_initial.py
message_sender/migrations/0002_auto_20161124_1150.py
message_sender/migrations/0003_auto_20161124_1357.py
message_sender/migrations/0004_outbound_last_sent_time.py
message_sender/migrations/0005_outbound_call_answered.py
message_sender/migrations/0006_add_created_at_index.py
message_sender/migrations/0007_add_to_addr_index.py
message_sender/migrations/0007_outboundsendfailure.py
message_sender/migrations/0008_auto_20170323_1042.py
message_sender/migrations/0009_auto_20170323_1453.py
message_sender/migrations/0010_merge.py
message_sender/migrations/0011_channel.py
message_sender/migrations/0012_channel_insert.py
message_sender/migrations/0013_outbound_channel.py
message_sender/migrations/0014_auto_20170503_1248.py
message_sender/migrations/0015_identitylookup.py
message_sender/migrations/0016_outbound_resend.py
message_sender/migrations/0017_auto_20180220_1329.py
message_sender/migrations/0018_auto_20180316_1305.py
message_sender/migrations/0019_auto_20180319_1446.py
message_sender/migrations/0020_outboundsendfailure_db_backed_fk_constraint.py
message_sender/migrations/0021_auto_20180504_1446.py
message_sender/migrations/0022_auto_20180914_1426.py
message_sender/migrations/0023_auto_20180926_0741.py
message_sender/migrations/0024_increase_inbound_message_content_limit.py
message_sender/migrations/0025_auto_20181116_0832.py
seed_message_sender-0.10.11.dist-info/LICENCE
seed_message_sender-0.10.11.dist-info/METADATA
seed_message_sender-0.10.11.dist-info/WHEEL
seed_message_sender-0.10.11.dist-info/top_level.txt
seed_message_sender-0.10.11.dist-info/RECORD
