Metadata-Version: 2.1
Name: seed-message-sender
Version: 0.10.11
Summary: Seed Message Sender mircoservice
Home-page: http://github.com/praekelt/seed-message-sender
Author: Praekelt.org
Author-email: dev@praekelt.org
License: BSD
Platform: UNKNOWN
Classifier: Development Status :: 4 - Beta
Classifier: Framework :: Django
Classifier: License :: OSI Approved :: BSD License
Classifier: Programming Language :: Python
Classifier: Programming Language :: Python :: 3.6
Classifier: Topic :: Software Development :: Libraries :: Python Modules
Requires-Dist: Django (==2.2.8)
Requires-Dist: djangorestframework (==3.9.1)
Requires-Dist: dj-database-url (==0.5.0)
Requires-Dist: psycopg2 (==2.7.5)
Requires-Dist: raven (==6.9.0)
Requires-Dist: django-filter (==2.0.0)
Requires-Dist: celery (==4.2.1)
Requires-Dist: pytz (==2018.5)
Requires-Dist: django-rest-hooks (==1.5.0)
Requires-Dist: go-http (==0.3.2)
Requires-Dist: django-redis (==4.10.0)
Requires-Dist: seed-services-client (==0.37.0)
Requires-Dist: django-getenv (==1.3.2)
Requires-Dist: django-storages (==1.7.1)
Requires-Dist: boto3 (==1.9.4)
Requires-Dist: coreapi (==2.3.3)
Requires-Dist: phonenumberslite (==8.9.14)
Requires-Dist: django-prometheus (==1.0.15)
